viewser/__init__.py
viewser/cli.py
viewser/commands/__init__.py
viewser/commands/config/__init__.py
viewser/commands/config/cli.py
viewser/commands/documentation/__init__.py
viewser/commands/documentation/cli.py
viewser/commands/documentation/formatting.py
viewser/commands/documentation/operations.py
viewser/commands/documentation/wrapped_views_doc.py
viewser/commands/help/__init__.py
viewser/commands/help/cli.py
viewser/commands/help/operations.py
viewser/commands/logs/__init__.py
viewser/commands/logs/cli.py
viewser/commands/model/__init__.py
viewser/commands/model/cli.py
viewser/commands/model/formatting.py
viewser/commands/model/models.py
viewser/commands/notebooks/__init__.py
viewser/commands/notebooks/cli.py
viewser/commands/notebooks/operations.py
viewser/commands/queryset/__init__.py
viewser/commands/queryset/cli.py
viewser/commands/queryset/config_drift.py
viewser/commands/queryset/drift_detection.py
viewser/commands/queryset/formatting.py
viewser/commands/queryset/integrity_checks.py
viewser/commands/queryset/models/__init__.py
viewser/commands/queryset/models/column.py
viewser/commands/queryset/models/queryset.py
viewser/commands/queryset/models/transform.py
viewser/commands/queryset/models/util.py
viewser/commands/queryset/operations.py
viewser/commands/queryset/queryset_list.py
viewser/commands/queryset/self_test.py
viewser/commands/system/__init__.py
viewser/commands/system/cli.py
viewser/commands/system/formatting.py
viewser/commands/system/models.py
viewser/error_handling/__init__.py
viewser/error_handling/checks.py
viewser/error_handling/error_handling.py
viewser/error_handling/errors.py
viewser/error_handling/exceptions.py
viewser/hirearchical_dict.py
viewser/operations.py
viewser/remotes.py
viewser/settings/__init__.py
viewser/settings/config_resolver.py
viewser/settings/db.py
viewser/settings/defaults.py
viewser/settings/exceptions.py
viewser/settings/interactive.py
viewser/settings/models.py
viewser/settings/static.py
viewser-6.6.4.dist-info/LICENSE
viewser-6.6.4.dist-info/METADATA
viewser-6.6.4.dist-info/WHEEL
viewser-6.6.4.dist-info/entry_points.txt
viewser-6.6.4.dist-info/RECORD
