Metadata-Version: 2.1
Name: viewser
Version: 6.6.4
Summary: The Views 3 CLI tool
Home-page: https://www.github.com/prio-data/viewser
License: CC-BY-NC
Author: peder2911
Author-email: pglandsverk@gmail.com
Requires-Python: >=3.9,<4.0
Classifier: License :: Other/Proprietary License
Classifier: Programming Language :: Python :: 3
Classifier: Programming Language :: Python :: 3.9
Classifier: Programming Language :: Python :: 3.10
Classifier: Programming Language :: Python :: 3.11
Classifier: Programming Language :: Python :: 3.12
Classifier: Programming Language :: Python :: 3.13
Requires-Dist: PyMonad (>=2.4.0,<3.0.0)
Requires-Dist: click (>=8.0.1,<9.0.0)
Requires-Dist: colorama (>=0.4.4,<0.5.0)
Requires-Dist: crayons (>=0.4.0,<0.5.0)
Requires-Dist: docker (>=5.0.0,<6.0.0)
Requires-Dist: environs (>=9.3.1,<10.0.0)
Requires-Dist: fitin (>=0.2.0,<0.3.0)
Requires-Dist: ipython (>=8.0.0,<9.0.0)
Requires-Dist: numpy (>=1.2.0,<2.0.0)
Requires-Dist: pandas (>=1.4.0,<2.0.0)
Requires-Dist: psutil (>=5.8.0,<6.0.0)
Requires-Dist: pyarrow (>9.0.0)
Requires-Dist: pydantic (>=2.0.0,<3.0.0)
Requires-Dist: pyod (<1.1.0)
Requires-Dist: requests (>=2.27.1,<3.0.0)
Requires-Dist: strconv (>=0.4.2,<0.5.0)
Requires-Dist: tabulate (>=0.8.9,<0.9.0)
Requires-Dist: toml (>=0.10.2,<0.11.0)
Requires-Dist: toolz (>=0.11.1,<0.12.0)
Requires-Dist: tqdm (>=4.66.0,<5.0.0)
Requires-Dist: views-schema (>=2.3.0,<3.0.0)
Requires-Dist: views-storage (>=1.1.0,<2.0.0)
Requires-Dist: views_tensor_utilities (>=1.0.0)
